pypoison/__init__.py
pypoison/_impl.py
pypoison-0.0.2.dist-info/LICENSE
pypoison-0.0.2.dist-info/METADATA
pypoison-0.0.2.dist-info/WHEEL
pypoison-0.0.2.dist-info/top_level.txt
pypoison-0.0.2.dist-info/RECORD
