Metadata-Version: 2.1
Name: pypoison
Version: 0.0.2
Summary: Nothing says "DO NOT USE" like a poison value.
Home-page: https://github.com/BenWiederhake/pypoison
Author: Ben Wiederhake
Author-email: BenWiederhake.GitHub@gmx.de
License: MIT
Keywords: pypoison
Platform: Any
Classifier: License :: OSI Approved :: MIT License
Classifier: Programming Language :: Python :: 3
Classifier: Programming Language :: Python :: 3.5
Classifier: Programming Language :: Python :: 3.6
Classifier: Programming Language :: Python :: 3.7
Classifier: Programming Language :: Python :: 3.8
